medialog.controlpanel-1.5-py3.8-nspkg.pth
medialog/controlpanel/__init__.py
medialog/controlpanel/configure.zcml
medialog/controlpanel/controlpanel.py
medialog/controlpanel/interfaces.py
medialog/controlpanel/my_controlpanel_icon.png
medialog/controlpanel/tests.py
medialog/controlpanel/profiles/default/controlpanel.xml
medialog/controlpanel/profiles/default/metadata.xml
medialog/controlpanel/profiles/default/registry.xml
medialog/controlpanel/profiles/uninstall/controlpanel.xml
medialog/controlpanel/profiles/uninstall/registry.xml
medialog.controlpanel-1.5.dist-info/METADATA
medialog.controlpanel-1.5.dist-info/WHEEL
medialog.controlpanel-1.5.dist-info/entry_points.txt
medialog.controlpanel-1.5.dist-info/namespace_packages.txt
medialog.controlpanel-1.5.dist-info/top_level.txt
medialog.controlpanel-1.5.dist-info/RECORD
