Metadata-Version: 2.1
Name: medialog.controlpanel
Version: 1.5
Summary: A pluggable control panel.
Home-page: https://github.com/espenmn/medialog.controlpanel
Author: Espen Moe-Nilssen
Author-email: espen@medialog.no
License: GPL
Classifier: Framework :: Plone
Classifier: Programming Language :: Python
Requires-Dist: plone.app.registry
